{
"users": [
  
    {
      "id": "x",
      "pass": "1234",
      "value": 22.530864197530864,
      "weight": "73"
    },
    {
      "id": "Pongsakorn Reabroy",
      "value": 17.913832199546484,
      "weight": "79"
    },
    {
      "id": "ราเบีย",
      "value": 21.564544913741823,
      "weight": "58"
    },
    {
      "id": 1,
      "value": 21.564544913741823,
      "weight": "58"
    },
    {
      "id": 2,
      "value": 21.564544913741823,
      "weight": "58"
    },
    {
      "id": 3,
      "value": 21.564544913741823,
      "weight": "58"
    },
    {
      "id": 4,
      "value": 21.564544913741823,
      "weight": "58"
    }
  ]
}
